scbase/__init__.py
scbase/cli.py
scbase/scbase.py
scbase/utils.py
scbase/stan/bb.pkl
scbase/stan/pg.pkl
scbase/stan/zipg.pkl
scbase/stan/zoibb.pkl
scbase-0.1.1.data/scripts/run_mcmc_on_cluster.sh
scbase-0.1.1.dist-info/AUTHORS.rst
scbase-0.1.1.dist-info/LICENSE
scbase-0.1.1.dist-info/METADATA
scbase-0.1.1.dist-info/WHEEL
scbase-0.1.1.dist-info/entry_points.txt
scbase-0.1.1.dist-info/top_level.txt
scbase-0.1.1.dist-info/RECORD
