Metadata-Version: 2.1
Name: scbase
Version: 0.1.1
Summary: **scBASE** is a python implementation of "soft" zero-and-one inflated model for estimating cellular allelic proportions from scRNA-Seq data
Home-page: https://github.com/churchill-lab/scBASE
Author: Kwangbom "KB" Choi, Ph.D.
Author-email: kb.choi@jax.org
License: MIT license
Keywords: scbase
Platform: UNKNOWN
Classifier: Development Status :: 4 - Beta
Classifier: Intended Audience :: Developers
Classifier: License :: OSI Approved :: MIT License
Classifier: Natural Language :: English
Classifier: Programming Language :: Python :: 3
Classifier: Programming Language :: Python :: 3.6
Classifier: Programming Language :: Python :: 3.7
Requires-Dist: numpy
Requires-Dist: scipy
Requires-Dist: Click (>=6.0)
Requires-Dist: pystan (>=2.17)
Requires-Dist: h5py (>=2.8)
Requires-Dist: pandas (>=0.23.4)
Requires-Dist: loompy (>=2.0.14)
Requires-Dist: future
Requires-Dist: six
